custom_nmt/__init__.py
custom_nmt/_exceptions.py
custom_nmt/_model_helpers.py
custom_nmt/constants.py
custom_nmt/models.py
custom_nmt/network_graph.py
custom_nmt/process_data.py
custom_nmt-0.1.3.dist-info/WHEEL
custom_nmt-0.1.3.dist-info/METADATA
custom_nmt-0.1.3.dist-info/RECORD
